odoo8_addon_business_requirement_deliverable_resource_template_categ-8.0.1.0.0-py2.7-nspkg.pth
odoo8_addon_business_requirement_deliverable_resource_template_categ-8.0.1.0.0.dist-info/DESCRIPTION.rst
odoo8_addon_business_requirement_deliverable_resource_template_categ-8.0.1.0.0.dist-info/METADATA
odoo8_addon_business_requirement_deliverable_resource_template_categ-8.0.1.0.0.dist-info/RECORD
odoo8_addon_business_requirement_deliverable_resource_template_categ-8.0.1.0.0.dist-info/WHEEL
odoo8_addon_business_requirement_deliverable_resource_template_categ-8.0.1.0.0.dist-info/metadata.json
odoo8_addon_business_requirement_deliverable_resource_template_categ-8.0.1.0.0.dist-info/namespace_packages.txt
odoo8_addon_business_requirement_deliverable_resource_template_categ-8.0.1.0.0.dist-info/top_level.txt
odoo_addons/business_requirement_deliverable_resource_template_categ/README.rst
odoo_addons/business_requirement_deliverable_resource_template_categ/__init__.py
odoo_addons/business_requirement_deliverable_resource_template_categ/__openerp__.py
odoo_addons/business_requirement_deliverable_resource_template_categ/models/__init__.py
odoo_addons/business_requirement_deliverable_resource_template_categ/models/business_requirement_resource_template.py
odoo_addons/business_requirement_deliverable_resource_template_categ/static/description/icon.png
odoo_addons/business_requirement_deliverable_resource_template_categ/static/img/bus_req_default.png
odoo_addons/business_requirement_deliverable_resource_template_categ/static/img/bus_req_default2.png
odoo_addons/business_requirement_deliverable_resource_template_categ/views/business_requirement_resource_template.xml
